test/__init__.py
test/test_urbitob.py
urbitob/__init__.py
urbitob/co.py
urbitob/ob.py
urbitob-0.0.4.dist-info/LICENSE
urbitob-0.0.4.dist-info/METADATA
urbitob-0.0.4.dist-info/WHEEL
urbitob-0.0.4.dist-info/top_level.txt
urbitob-0.0.4.dist-info/RECORD
