Metadata-Version: 2.1
Name: urbitob
Version: 0.0.4
Summary: A python implementation of urbit-ob
Home-page: https://github.com/evening/urbit-pob
Author: ~ranren-ranlen
Classifier: Programming Language :: Python :: 3
Requires-Python: >=3.6
License-File: LICENSE
Requires-Dist: mmh3 (==3.0)
